[{"objdata":"{\"type\":1,\"description\":\"rect\",\"isMouseOver\":false,\"display\":\"checked\",\"radian\":4.435720641302795,\"objectId\":\"Y8dqvOTo\",\"data\":{\"nx\":0,\"ny\":0,\"imgPatterns\":\"no-repeat\",\"rectBackGroundColor\":\"black\",\"rectBackGroundAlpha\":\"1\",\"rectBackGroundFillType\":\"image\",\"rectColor\":\"black\",\"rectAlpha\":\"1\",\"rectFillType\":\"rectfillnone\",\"rectBoader\":\"checked\",\"rectfontsize\":10,\"rectfontface\":\"Arial\",\"rectfontweight\":\"normal\",\"rectfontstyle\":\"normal\",\"rectfontfillstyle\":\"black\",\"recttextAlign\":\"center\",\"recttextbaseline\":\"middle\",\"initangle\":-1,\"eleImgAlpha\":\"1\",\"eleImgFillType\":\"fit\",\"eleImgOriWidth\":0,\"eleImgOriHeight\":0,\"lineWidth\":1,\"rotation\":0,\"textType\":\"rectdatadataset\",\"text\":\"temp_text\",\"dataSetText\":\"data1\",\"dcrawid\":-1,\"fontface\":\"Arial\",\"fontweight\":\"normal\",\"fontstyle\":\"normal\",\"textAlign\":\"center\",\"textBaseline\":\"middle\",\"fillStyle\":\"black\",\"maxwidth\":0,\"width\":240,\"height\":400,\"x\":214,\"y\":26,\"zindex\":0}}"}]